{"nodes": [{"id": "splc_page_splcpage", "label": "SPLc Compiler Page", "file_type": "code", "source_file": "spl/ui/streamlit/pages/4_\ud83d\udd27_SPLc.py", "source_location": null, "source_url": null, "captured_at": null, "author": null, "contributor": null}, {"id": "splc_page_find_spl_files", "label": "_find_spl_files", "file_type": "code", "source_file": "spl/ui/streamlit/pages/4_\ud83d\udd27_SPLc.py", "source_location": "line 82", "source_url": null, "captured_at": null, "author": null, "contributor": null}, {"id": "doda_pattern", "label": "DODA Design Once Deploy Anywhere", "file_type": "rationale", "source_file": "spl/ui/streamlit/pages/4_\ud83d\udd27_SPLc.py", "source_location": "line 47", "source_url": null, "captured_at": null, "author": null, "contributor": null}], "edges": [{"source": "splc_page_splcpage", "target": "splc_page_find_spl_files", "relation": "calls", "confidence": "EXTRACTED", "confidence_score": 1.0, "source_file": "spl/ui/streamlit/pages/4_\ud83d\udd27_SPLc.py", "source_location": "line 109", "weight": 1.0}, {"source": "splc_page_splcpage", "target": "ui_spl3_rag_bridge", "relation": "calls", "confidence": "EXTRACTED", "confidence_score": 1.0, "source_file": "spl/ui/streamlit/pages/4_\ud83d\udd27_SPLc.py", "source_location": "line 17", "weight": 1.0}, {"source": "splc_page_splcpage", "target": "doda_pattern", "relation": "references", "confidence": "EXTRACTED", "confidence_score": 1.0, "source_file": "spl/ui/streamlit/pages/4_\ud83d\udd27_SPLc.py", "source_location": "line 47", "weight": 1.0}, {"source": "doda_pattern", "target": "splc_page_splcpage", "relation": "rationale_for", "confidence": "EXTRACTED", "confidence_score": 1.0, "source_file": "spl/ui/streamlit/pages/4_\ud83d\udd27_SPLc.py", "source_location": "line 47", "weight": 1.0}], "hyperedges": []}