{"nodes": [{"id": "storage_memory_memorystore", "label": "MemoryStore", "file_type": "code", "source_file": "spl/storage/memory.py", "source_location": "line 17", "source_url": null, "captured_at": null, "author": null, "contributor": null}, {"id": "dd_cache_diskcache", "label": "DiskCache (dd-cache)", "file_type": "code", "source_file": "spl/storage/memory.py", "source_location": null, "source_url": null, "captured_at": null, "author": null, "contributor": null}], "edges": [{"source": "storage_memory_memorystore", "target": "dd_cache_diskcache", "relation": "calls", "confidence": "EXTRACTED", "confidence_score": 1.0, "source_file": "spl/storage/memory.py", "source_location": "line 29", "weight": 1.0}], "hyperedges": []}